{
  "updatedAt": "2026-05-28T04:39:18.747Z",
  "baseId": "apprsAm2FOohEmL2u",
  "tableId": "tbl0K0nFQL64jQMx8",
  "updatedCount": 8,
  "results": [
    {
      "recordId": "rec9QQkOryhKitjDW",
      "itemTitle": "Thorens TD-160 Shopify Live",
      "workflowStatus": "Listed, Shopify",
      "sku": "SAMPLE-WORKFLOW-QUEUE-13",
      "folderId": "11qLUNAjZ_CUEatS8aoQD3q_PAiWOme5O",
      "photoUrls": [
        "https://drive.google.com/uc?export=view&id=1U6iROyZKlC5uBLBLYE_eMSE3G5BkmLpm",
        "https://drive.google.com/uc?export=view&id=1IznFhh-uFF82kx6-FzHPAFiAfI28DznO",
        "https://drive.google.com/uc?export=view&id=1j7YZqhirlPc4vHCzbqamu8yfdXXmFMYH"
      ],
      "testingUrls": [
        "https://drive.google.com/uc?export=view&id=1xoyQPHk-NLIGgKh5NcDJ9a5knkJoJV7L",
        "https://drive.google.com/uc?export=view&id=1kmMCjCDKbfrgr_sWmTmrutH8J2Z1_FHl",
        "https://drive.google.com/uc?export=view&id=1I7OzovDK-s4_URBsOaMXCF65sl-qUgkb"
      ],
      "updatedRecordId": "rec9QQkOryhKitjDW"
    },
    {
      "recordId": "reccW7p0t2qZX5Gi5",
      "itemTitle": "JBL L100 Stale eBay",
      "workflowStatus": "Stale Listing, eBay",
      "sku": "SAMPLE-WORKFLOW-QUEUE-16",
      "folderId": "1mkMZxWMz-uqWt-zcN15FLP5TcC3FpaRL",
      "photoUrls": [
        "https://drive.google.com/uc?export=view&id=1NuTgllAI8bED5wibWmjCD9lYB86UVb24",
        "https://drive.google.com/uc?export=view&id=1Y_ZKQjAN7LgVf8muXzvFm_4OsZHEAHTr",
        "https://drive.google.com/uc?export=view&id=1R5LK0YX75QO0pXMtOf0NLSTJ-5fpMvex"
      ],
      "testingUrls": [
        "https://drive.google.com/uc?export=view&id=1yqSsxXUwkBKNfLj-189rAmiVPODWUPS6",
        "https://drive.google.com/uc?export=view&id=1Y0pJs3WqQCBmcTwADjFbA2URjIWsFjnx",
        "https://drive.google.com/uc?export=view&id=1ieVK7LVLSuI35piqiboMZpf0VtjIoqMj"
      ],
      "updatedRecordId": "reccW7p0t2qZX5Gi5"
    },
    {
      "recordId": "reccg0SUYaislHDJt",
      "itemTitle": "Marantz 2230 eBay Live",
      "workflowStatus": "Listed, eBay",
      "sku": "SAMPLE-WORKFLOW-QUEUE-14",
      "folderId": "1XnF_YGfc5AyCGaodGNCJs4yGWwULo0TG",
      "photoUrls": [
        "https://drive.google.com/uc?export=view&id=1oU6KhNVTwDkO4Qp6QTxej1hEHt77LTAy",
        "https://drive.google.com/uc?export=view&id=1dD-5hkAo9z3zEXFPZsMsA8Uh3seq79uv",
        "https://drive.google.com/uc?export=view&id=1KR9VGMaPGxZVsDRLZtZdpE3I-S35GaGn"
      ],
      "testingUrls": [
        "https://drive.google.com/uc?export=view&id=1FRZbGPzisBE6aoyB09PBB5ACkeYWFvzq",
        "https://drive.google.com/uc?export=view&id=1jhM2nRPMguNCJgRcHhPLVHXcRkq99Rxa",
        "https://drive.google.com/uc?export=view&id=1D0w9QFkO0Ih62YF-1qXe4lQ_CAJmbKmV"
      ],
      "updatedRecordId": "reccg0SUYaislHDJt"
    },
    {
      "recordId": "receF21tiOq7kO0av",
      "itemTitle": "Tandberg 3014A Shipped",
      "workflowStatus": "Shipped",
      "sku": "SAMPLE-WORKFLOW-QUEUE-18",
      "folderId": "1X1G3dGnCYs5N_26REBHztjAxQy1nLM8u",
      "photoUrls": [
        "https://drive.google.com/uc?export=view&id=1HS6VljZHuG88lHINHFTY9yl6YxKzaiNz",
        "https://drive.google.com/uc?export=view&id=1Nj5N6mKVq6QjJJ3jfeP1ldakwpFZc4sO",
        "https://drive.google.com/uc?export=view&id=1Oe5_kDMMzKjLSFeft9o8vai46Bqf76VQ"
      ],
      "testingUrls": [
        "https://drive.google.com/uc?export=view&id=17OiQ_ju_GD3QVjnWyjBEQaRSAsMF3qBZ",
        "https://drive.google.com/uc?export=view&id=1Ym1N24pe1BwDoy197ktkNYvWfiO94uTC",
        "https://drive.google.com/uc?export=view&id=1ywAwHJl5efcr2oriKoLT1DtT2-e1uVGj"
      ],
      "updatedRecordId": "receF21tiOq7kO0av"
    },
    {
      "recordId": "reck8bUFT7Ne2qukd",
      "itemTitle": "Oracle Alexandria Stale Shopify",
      "workflowStatus": "Stale Listing, Shopify",
      "sku": "SAMPLE-WORKFLOW-QUEUE-15",
      "folderId": "1qLxEoOAguwDiMk4aSfStYu_5RUJsrs35",
      "photoUrls": [
        "https://drive.google.com/uc?export=view&id=1Hmrdzp7A-tzz-xAGDuwelVD1iQKD8PqL",
        "https://drive.google.com/uc?export=view&id=17v4ILqXvy2yr7bA_GL5i-UCoPx0CPCli",
        "https://drive.google.com/uc?export=view&id=1vMJay5azdq1F7_Mr2ld4fcxqUoToB51F"
      ],
      "testingUrls": [
        "https://drive.google.com/uc?export=view&id=10taWvovZOuPKepn_6HuZ62DtxRUFidlY",
        "https://drive.google.com/uc?export=view&id=17SeXFy66kl_OjRKvre2fWbmgMMPdPZK_",
        "https://drive.google.com/uc?export=view&id=1uxJJ2IERF4yikOkpTIwMFrFLUnCjL8eb"
      ],
      "updatedRecordId": "reck8bUFT7Ne2qukd"
    },
    {
      "recordId": "rect5r3VkSf034NPL",
      "itemTitle": "Audio Research SP-9 Pre-Listing",
      "workflowStatus": "Awaiting Pre-Listing Review",
      "sku": "SAMPLE-WORKFLOW-QUEUE-11",
      "folderId": "1oF-hfsWo7_m-BmEX5A2vqps_v6EOkLhJ",
      "photoUrls": [
        "https://drive.google.com/uc?export=view&id=197Gdw-TwkopbFZFksatt4lAnXUEVJpms",
        "https://drive.google.com/uc?export=view&id=1sscscxLRdTQMX7JhbDlNVfUXZ3zaGi36",
        "https://drive.google.com/uc?export=view&id=1COTjVbBapj0XsJjAEPpqenCpw1UwO9nb"
      ],
      "testingUrls": [
        "https://drive.google.com/uc?export=view&id=1ubK5Q7W_DlSuM6PVTpxorrjVZ036mJ41",
        "https://drive.google.com/uc?export=view&id=1Ajx5lgBuA84H-EnecO8DQDIhhMw4gOtb",
        "https://drive.google.com/uc?export=view&id=16ujvZabR5_Tj6ZeXgcen89gw-dIANUeY"
      ],
      "updatedRecordId": "rect5r3VkSf034NPL"
    },
    {
      "recordId": "recwz1E6jmEk8tUYb",
      "itemTitle": "Klipsch Cornwall Sold Ready",
      "workflowStatus": "Sold - Ready to Ship",
      "sku": "SAMPLE-WORKFLOW-QUEUE-17",
      "folderId": "1f-mNXgmpcPLBwNX_lcsZRJGmVvaCZN6U",
      "photoUrls": [
        "https://drive.google.com/uc?export=view&id=1Dc70XnJ-EReuYOdwXXZS1FlIZ82lyeAh",
        "https://drive.google.com/uc?export=view&id=1fsQNIuGMpt0J4tiDC7qdAMBO_OvmdWgP",
        "https://drive.google.com/uc?export=view&id=1Wde_9Be7p_nWvf0m0S1E2GonrRl1O7l9"
      ],
      "testingUrls": [
        "https://drive.google.com/uc?export=view&id=1xsNsWdjU4Z-sT_ko5Qh_DaKJtmeNfIh8",
        "https://drive.google.com/uc?export=view&id=1E8fMBcXLnAZdjpUaNxwx0bpu96vbIyUO",
        "https://drive.google.com/uc?export=view&id=1Oe4IJLnjgfaHYy0V2TwIqBpESHDba6Qr"
      ],
      "updatedRecordId": "recwz1E6jmEk8tUYb"
    },
    {
      "recordId": "reczN4jA3s0hm4lZD",
      "itemTitle": "Rega Planar 8 Publish Ready",
      "workflowStatus": "Approved for Publish",
      "sku": "SAMPLE-WORKFLOW-QUEUE-12",
      "folderId": "1eSBw_Q7gic0oMUowOGxfN-P_J3h5CuHI",
      "photoUrls": [
        "https://drive.google.com/uc?export=view&id=1b0Uej_GtiJVsx_e0MX35FFxCX-7umQd-",
        "https://drive.google.com/uc?export=view&id=1Phczy-GpwIOuh2Axvtg2d7dGdS8jCLjc",
        "https://drive.google.com/uc?export=view&id=1PkXhPaiK4cdCKLpG8VpTgmOrD8qa5ipf"
      ],
      "testingUrls": [
        "https://drive.google.com/uc?export=view&id=1y7_KCbFfUuX0hvscwbfpa_riH75OTiUr",
        "https://drive.google.com/uc?export=view&id=1rThBjdLW5I6285OCkH4rqXW1ZmhprcBn",
        "https://drive.google.com/uc?export=view&id=10_HGWEEniLi1Lm4tPc0JOY6pZfoPjZiB"
      ],
      "updatedRecordId": "reczN4jA3s0hm4lZD"
    }
  ]
}
